nx3d/__init__.py
nx3d/__main__.py
nx3d/core.py
nx3d/examples/__init__.py
nx3d/examples/diffusion.py
nx3d/examples/gameoflife.py
nx3d/examples/keyboard_control.py
nx3d/mesh.py
nx3d/simplified.py
nx3d/types.py
nx3d/utils.py
nx3d-22.11.0.dist-info/LICENSE
nx3d-22.11.0.dist-info/WHEEL
nx3d-22.11.0.dist-info/METADATA
nx3d-22.11.0.dist-info/RECORD
