Metadata-Version: 2.1
Name: nx3d
Version: 22.11.0
Summary: A 3D plotting library for networkx
Home-page: https://github.com/ekalosak/nx3d
License: MIT
Author: Eric Kalosa-Kenyon
Author-email: helloateric@gmail.com
Requires-Python: >=3.9,<3.12
Classifier: License :: OSI Approved :: MIT License
Classifier: Operating System :: OS Independent
Classifier: Programming Language :: Python :: 3
Classifier: Programming Language :: Python :: 3.9
Classifier: Programming Language :: Python :: 3.10
Classifier: Programming Language :: Python :: 3.11
Classifier: Programming Language :: Python :: 3
Requires-Dist: Panda3D (>=1.10,<2.0)
Requires-Dist: loguru (>=0.6.0,<0.7.0)
Requires-Dist: networkx (>=2.8,<3.0)
Requires-Dist: numpy (>=1.23,<2.0)
Requires-Dist: pyvista (>=0.36.1,<0.37.0)
